scrapper_json_jawron/__init__.py
scrapper_json_jawron/cleaner.py
scrapper_json_jawron/scrapper.py
scrapper_json_jawron-0.3.1.dist-info/METADATA
scrapper_json_jawron-0.3.1.dist-info/WHEEL
scrapper_json_jawron-0.3.1.dist-info/licenses/LICENSE
scrapper_json_jawron-0.3.1.dist-info/RECORD
